Workbook

Sheet Start here
B2: WB Group ERP — Acceptance Scripts
B3: User acceptance testing in Pre-Prod · September 2026 · 97 checks across 12 roles
B5: WHERE AND HOW
B6: 1. Open Pre-Prod at wberp-pre-prod.up.railway.app. Never test in the live system.
B7: 2. Sign in with the login made for your role, and open that role's sheet (tabs along the bottom). Ask the administrator if you have no login. Do not share a login — every action is recorded against the name that did it.
B8: 3. Choose WBE — WB Engineering in the company switcher unless a step says otherwise. Test records are marked: items and stores start with T-, notes say [test data]. Examples: supplier Emirates Cable Trading LLC, customer Deep Port Logistics FZC, item T-CBL-4C16, store T-MAIN.
B9: 4. Anything you create, name it with your initials, e.g. "AK test — cable for pump house", so it can be found later.
B10: 5. Follow the steps, compare what happens with the Expected result, and fill in the yellow cells. Use the ? button in the top bar of the system if a screen seems strange before marking it failed.
B11: 6. Save the workbook with your name in the file name and send it to the project team at the end of each testing day.
B13: THE CELLS YOU FILL IN
B14: Result | C14: Choose Pass, Fail, Blocked or Not run from the list. Left empty counts as Not run.
B15: Severity | C15: Only for Fail or Blocked: Critical, Major, Minor or Suggestion.
B16: What actually happened | C16: For a Fail: the screen, the figure and the message word for word. For Blocked: what stopped you.
B17: Tested by · Date | C17: Your name, and the date you ran the check (dd/mm/yyyy).
B19: RESULTS
B20: Pass | C20: What happened matches the expected result.
B21: Fail | C21: It did something different, showed an error, or showed a wrong figure.
B22: Blocked | C22: You could not run it — no login, no access, or an earlier check failed.
B23: Not run | C23: Not attempted yet.
B25: SEVERITY
B26: Critical | C26: Wrong money, wrong tax, data lost, or someone can see or do what they must not. Stops go-live.
B27: Major | C27: The task cannot be done, or only with a workaround a normal user would not find.
B28: Minor | C28: The task can be done, but something is confusing, slow or badly worded.
B29: Suggestion | C29: Works as designed, but you would like it to work differently.
B31: HOW THE ROLES HAND WORK TO EACH OTHER
B32: Buying: Site Engineer raises a material request → Site Engineer, Project Manager and Procurement approve → Procurement asks 3 suppliers and awards → Project Manager, Operations Manager and Director approve the order → Storekeeper receives → QA/QC inspects → Storekeeper issues to the job → Accounts sees the cost on the job.
B33: Selling: Estimator logs the enquiry and prices it → raises the quotation → Operations Manager and Director approve → Estimator emails it → customer orders and the job is created → Accounts invoices.
B34: Where a check depends on someone else's, the Depends on column says which.
B36: EXAMPLE — HOW A COMPLETED FAILED CHECK LOOKS (THIS ROW IS AN EXAMPLE ONLY)
B37: Check | C37: Result | D37: Severity | E37: What actually happened | I37: Tested by | J37: Date
B38: STR-02 | C38: Fail | D38: Major | E38: Delivery into T-MAIN saved without asking for a bin. Stock on Hand shows 20 of T-GLD-M25 in T-MAIN with no bin. | I38: Ahmed Khan | J38: 46286
B40: Every expected result was checked against the system's own rules and screens before it was written. If the system and this workbook disagree, record a Fail and say so — either one may be wrong, and both matter.

Sheet Summary
B2: Summary
B3: Counts update by themselves as results are chosen on each role's sheet.
B5: Role (sheet) | C5: Sign in as | D5: Checks | E5: Pass | F5: Fail | G5: Blocked | H5: Not run | I5: Done | J5: Critical | K5: Major | L5: Minor | M5: Suggestion
B6: Administrator | C6: Group Admin | D6: =COUNTA('Administrator'!$A$8:$A$300) | E6: =COUNTIF('Administrator'!$G$8:$G$300,"Pass") | F6: =COUNTIF('Administrator'!$G$8:$G$300,"Fail") | G6: =COUNTIF('Administrator'!$G$8:$G$300,"Blocked") | H6: =D6-E6-F6-G6 | I6: =IF(D6=0,0,(E6+F6+G6)/D6) | J6: =COUNTIF('Administrator'!$H$8:$H$300,"Critical") | K6: =COUNTIF('Administrator'!$H$8:$H$300,"Major") | L6: =COUNTIF('Administrator'!$H$8:$H$300,"Minor") | M6: =COUNTIF('Administrator'!$H$8:$H$300,"Suggestion")
B7: Estimator - Sales | C7: Estimation / Sales Engineer | D7: =COUNTA('Estimator - Sales'!$A$8:$A$300) | E7: =COUNTIF('Estimator - Sales'!$G$8:$G$300,"Pass") | F7: =COUNTIF('Estimator - Sales'!$G$8:$G$300,"Fail") | G7: =COUNTIF('Estimator - Sales'!$G$8:$G$300,"Blocked") | H7: =D7-E7-F7-G7 | I7: =IF(D7=0,0,(E7+F7+G7)/D7) | J7: =COUNTIF('Estimator - Sales'!$H$8:$H$300,"Critical") | K7: =COUNTIF('Estimator - Sales'!$H$8:$H$300,"Major") | L7: =COUNTIF('Estimator - Sales'!$H$8:$H$300,"Minor") | M7: =COUNTIF('Estimator - Sales'!$H$8:$H$300,"Suggestion")
B8: Operations & Directors | C8: Operations Manager, then Director | D8: =COUNTA('Operations & Directors'!$A$8:$A$300) | E8: =COUNTIF('Operations & Directors'!$G$8:$G$300,"Pass") | F8: =COUNTIF('Operations & Directors'!$G$8:$G$300,"Fail") | G8: =COUNTIF('Operations & Directors'!$G$8:$G$300,"Blocked") | H8: =D8-E8-F8-G8 | I8: =IF(D8=0,0,(E8+F8+G8)/D8) | J8: =COUNTIF('Operations & Directors'!$H$8:$H$300,"Critical") | K8: =COUNTIF('Operations & Directors'!$H$8:$H$300,"Major") | L8: =COUNTIF('Operations & Directors'!$H$8:$H$300,"Minor") | M8: =COUNTIF('Operations & Directors'!$H$8:$H$300,"Suggestion")
B9: Site Engineer | C9: Site Engineer / Planner | D9: =COUNTA('Site Engineer'!$A$8:$A$300) | E9: =COUNTIF('Site Engineer'!$G$8:$G$300,"Pass") | F9: =COUNTIF('Site Engineer'!$G$8:$G$300,"Fail") | G9: =COUNTIF('Site Engineer'!$G$8:$G$300,"Blocked") | H9: =D9-E9-F9-G9 | I9: =IF(D9=0,0,(E9+F9+G9)/D9) | J9: =COUNTIF('Site Engineer'!$H$8:$H$300,"Critical") | K9: =COUNTIF('Site Engineer'!$H$8:$H$300,"Major") | L9: =COUNTIF('Site Engineer'!$H$8:$H$300,"Minor") | M9: =COUNTIF('Site Engineer'!$H$8:$H$300,"Suggestion")
B10: Project Manager | C10: Project Manager | D10: =COUNTA('Project Manager'!$A$8:$A$300) | E10: =COUNTIF('Project Manager'!$G$8:$G$300,"Pass") | F10: =COUNTIF('Project Manager'!$G$8:$G$300,"Fail") | G10: =COUNTIF('Project Manager'!$G$8:$G$300,"Blocked") | H10: =D10-E10-F10-G10 | I10: =IF(D10=0,0,(E10+F10+G10)/D10) | J10: =COUNTIF('Project Manager'!$H$8:$H$300,"Critical") | K10: =COUNTIF('Project Manager'!$H$8:$H$300,"Major") | L10: =COUNTIF('Project Manager'!$H$8:$H$300,"Minor") | M10: =COUNTIF('Project Manager'!$H$8:$H$300,"Suggestion")
B11: Procurement | C11: Procurement Officer | D11: =COUNTA('Procurement'!$A$8:$A$300) | E11: =COUNTIF('Procurement'!$G$8:$G$300,"Pass") | F11: =COUNTIF('Procurement'!$G$8:$G$300,"Fail") | G11: =COUNTIF('Procurement'!$G$8:$G$300,"Blocked") | H11: =D11-E11-F11-G11 | I11: =IF(D11=0,0,(E11+F11+G11)/D11) | J11: =COUNTIF('Procurement'!$H$8:$H$300,"Critical") | K11: =COUNTIF('Procurement'!$H$8:$H$300,"Major") | L11: =COUNTIF('Procurement'!$H$8:$H$300,"Minor") | M11: =COUNTIF('Procurement'!$H$8:$H$300,"Suggestion")
B12: Storekeeper | C12: Storekeeper | D12: =COUNTA('Storekeeper'!$A$8:$A$300) | E12: =COUNTIF('Storekeeper'!$G$8:$G$300,"Pass") | F12: =COUNTIF('Storekeeper'!$G$8:$G$300,"Fail") | G12: =COUNTIF('Storekeeper'!$G$8:$G$300,"Blocked") | H12: =D12-E12-F12-G12 | I12: =IF(D12=0,0,(E12+F12+G12)/D12) | J12: =COUNTIF('Storekeeper'!$H$8:$H$300,"Critical") | K12: =COUNTIF('Storekeeper'!$H$8:$H$300,"Major") | L12: =COUNTIF('Storekeeper'!$H$8:$H$300,"Minor") | M12: =COUNTIF('Storekeeper'!$H$8:$H$300,"Suggestion")
B13: QA-QC & Calibration | C13: QA/QC & Calibration | D13: =COUNTA('QA-QC & Calibration'!$A$8:$A$300) | E13: =COUNTIF('QA-QC & Calibration'!$G$8:$G$300,"Pass") | F13: =COUNTIF('QA-QC & Calibration'!$G$8:$G$300,"Fail") | G13: =COUNTIF('QA-QC & Calibration'!$G$8:$G$300,"Blocked") | H13: =D13-E13-F13-G13 | I13: =IF(D13=0,0,(E13+F13+G13)/D13) | J13: =COUNTIF('QA-QC & Calibration'!$H$8:$H$300,"Critical") | K13: =COUNTIF('QA-QC & Calibration'!$H$8:$H$300,"Major") | L13: =COUNTIF('QA-QC & Calibration'!$H$8:$H$300,"Minor") | M13: =COUNTIF('QA-QC & Calibration'!$H$8:$H$300,"Suggestion")
B14: Accounts | C14: Finance / Accounts | D14: =COUNTA('Accounts'!$A$8:$A$300) | E14: =COUNTIF('Accounts'!$G$8:$G$300,"Pass") | F14: =COUNTIF('Accounts'!$G$8:$G$300,"Fail") | G14: =COUNTIF('Accounts'!$G$8:$G$300,"Blocked") | H14: =D14-E14-F14-G14 | I14: =IF(D14=0,0,(E14+F14+G14)/D14) | J14: =COUNTIF('Accounts'!$H$8:$H$300,"Critical") | K14: =COUNTIF('Accounts'!$H$8:$H$300,"Major") | L14: =COUNTIF('Accounts'!$H$8:$H$300,"Minor") | M14: =COUNTIF('Accounts'!$H$8:$H$300,"Suggestion")
B15: Finance Controller | C15: Finance Controller | D15: =COUNTA('Finance Controller'!$A$8:$A$300) | E15: =COUNTIF('Finance Controller'!$G$8:$G$300,"Pass") | F15: =COUNTIF('Finance Controller'!$G$8:$G$300,"Fail") | G15: =COUNTIF('Finance Controller'!$G$8:$G$300,"Blocked") | H15: =D15-E15-F15-G15 | I15: =IF(D15=0,0,(E15+F15+G15)/D15) | J15: =COUNTIF('Finance Controller'!$H$8:$H$300,"Critical") | K15: =COUNTIF('Finance Controller'!$H$8:$H$300,"Major") | L15: =COUNTIF('Finance Controller'!$H$8:$H$300,"Minor") | M15: =COUNTIF('Finance Controller'!$H$8:$H$300,"Suggestion")
B16: HR | C16: HR Officer | D16: =COUNTA('HR'!$A$8:$A$300) | E16: =COUNTIF('HR'!$G$8:$G$300,"Pass") | F16: =COUNTIF('HR'!$G$8:$G$300,"Fail") | G16: =COUNTIF('HR'!$G$8:$G$300,"Blocked") | H16: =D16-E16-F16-G16 | I16: =IF(D16=0,0,(E16+F16+G16)/D16) | J16: =COUNTIF('HR'!$H$8:$H$300,"Critical") | K16: =COUNTIF('HR'!$H$8:$H$300,"Major") | L16: =COUNTIF('HR'!$H$8:$H$300,"Minor") | M16: =COUNTIF('HR'!$H$8:$H$300,"Suggestion")
B17: Site Timekeeper | C17: Site Timekeeper | D17: =COUNTA('Site Timekeeper'!$A$8:$A$300) | E17: =COUNTIF('Site Timekeeper'!$G$8:$G$300,"Pass") | F17: =COUNTIF('Site Timekeeper'!$G$8:$G$300,"Fail") | G17: =COUNTIF('Site Timekeeper'!$G$8:$G$300,"Blocked") | H17: =D17-E17-F17-G17 | I17: =IF(D17=0,0,(E17+F17+G17)/D17) | J17: =COUNTIF('Site Timekeeper'!$H$8:$H$300,"Critical") | K17: =COUNTIF('Site Timekeeper'!$H$8:$H$300,"Major") | L17: =COUNTIF('Site Timekeeper'!$H$8:$H$300,"Minor") | M17: =COUNTIF('Site Timekeeper'!$H$8:$H$300,"Suggestion")
B18: All roles | D18: =SUM(D6:D17) | E18: =SUM(E6:E17) | F18: =SUM(F6:F17) | G18: =SUM(G6:G17) | H18: =SUM(H6:H17) | I18: =IF(D18=0,0,(E18+F18+G18)/D18) | J18: =SUM(J6:J17) | K18: =SUM(K6:K17) | L18: =SUM(L6:L17) | M18: =SUM(M6:M17)
B20: Go-live needs every check Pass, and no open Critical or Major.
B21: Readiness | C21: =IF(AND(E18=D18,J18+K18=0),"Ready for sign-off",IF(J18+K18>0,"Not ready — Critical or Major failures open","In progress — "&TEXT(I18,"0%")&" of checks run"))
B22: Severity counts include Blocked checks that were given a severity.

Sheet Administrator
A1: Administrator
A2: Sign in as: | C2: Group Admin
A3: Sets up the companies, the letterhead on printed documents, email, users and who may approve what. Run these first: several other roles depend on them.
A4: Tester: | E4: Yellow cells are yours to fill in. Result and Severity have drop-down lists.
A5: ← Back to Summary
A7: Check | B7: Area | C7: Title | D7: Steps | E7: Expected result | F7: Depends on | G7: Result | H7: Severity | I7: What actually happened | J7: Tested by | K7: Date
A8: ADM-01 | B8: Finance & HR | C8: Complete a company's legal details | D8: 1. Open Companies and edit WBE. 2. Enter the VAT registration number (TRN) with spaces, as printed on the certificate. 3. Enter the address line and city, and choose the emirate. 4. Save, then open the record again. | E8: The details are kept. The TRN is stored without the spaces. The emirate is chosen from the seven, not typed.
A9: ADM-02 | B9: CRM, Inventory & documents | C9: Set the letterhead for printed documents | D9: 1. Open Settings → Printed Documents and choose WBE at the top. 2. Set the accent colour, phone, email and website, and a footer line such as the trade licence number. 3. Paste standard terms into Quotation terms, Purchase order terms and Enquiry (RFQ) terms. 4. Save. 5. Click Print next to “See it on paper”. | E9: A PDF opens with SAMPLE across the page, your contact details under the company name, the TRN, the accent colour on the title and rules, your quotation terms, the footer line at the bottom and “Page 1 of 1”.
A10: ADM-03 | B10: CRM, Inventory & documents | C10: Use the company's own letterhead artwork | D10: 1. On Settings → Printed Documents, choose a PNG or JPEG of the letterhead band as Header artwork. 2. Save and print the sample again. 3. Now try choosing an SVG, GIF or PDF file as the artwork. | E10: The sample shows the artwork across the top instead of the name and logo. The SVG, GIF or PDF is refused with a message asking for a PNG or JPEG.
A11: ADM-04 | B11: CRM, Inventory & documents | C11: Warnings for missing company details | D11: 1. On Settings → Printed Documents, switch to a company with no TRN or no address recorded. | E11: A yellow warning says what is missing and links to Companies. Documents for that company still print, with the name only.
A12: ADM-05 | B12: CRM, Inventory & documents | C12: Connect the mail server | D12: 1. Open Settings → Email and choose the provider. 2. Enter the mailbox, its password or app password, and the send-as name and address. 3. Save, then Send a test to your own address. | E12: The test email arrives. If it does not, the screen shows the mail server's own message, which can be given to IT. The password is not shown again after saving. | F12: Needs a real mailbox from IT. Mark Blocked if there is none yet.
A13: ADM-06 | B13: Finance & HR | C13: Create a login for each tester | D13: 1. Open Users and add a user for each role on this page, giving each the role and the companies they work in. 2. Note the temporary password shown. 3. Sign in as one of them in a private window. | E13: The temporary password is shown once. The new user must set their own password before they can go any further.
A14: ADM-07 | B14: Finance & HR | C14: Access follows the role | D14: 1. Sign in as the Storekeeper. 2. Look at the menu, then type /finance at the end of the address and press Enter. | E14: Finance is not in the menu. Typing the address returns you to the dashboard without showing any of the Finance screen.
A15: ADM-08 | B15: CRM, Inventory & documents | C15: Changing a role's access survives the next release | D15: 1. Open Access Control and remove one screen from the Storekeeper role, e.g. Returns from Site. 2. Ask the project team to note it, and re-check after the next update is deployed to Pre-Prod. | E15: After the update the Storekeeper still does not have that screen. Changes made here are never reset by a new release. | F15: Needs a deployment between the two halves. Leave as Not run until then.
A16: ADM-09 | B16: CRM, Inventory & documents | C16: Approval routes are as agreed | D16: 1. Open Approvals → Configure routes. | E16: Material Request: Site Engineer / Planner → Project Manager → Procurement Officer. Purchase Order: Project Manager → Operations Manager → Director, plus Managing Director from AED 50,000. Sales Quotation: Operations Manager → Director, plus Managing Director from AED 500,000.
A17: ADM-10 | B17: Finance & HR | C17: The audit trail shows who changed what | D17: 1. Open Audit Log and search for “Printed document settings”. 2. Search for your own name. | E17: Your change is listed with the time and your name. The artwork itself is not dumped into the log. Nothing in the log can be edited or deleted.
A18: ADM-11 | B18: Finance & HR | C18: Give someone a second company | D18: 1. Open Users & Roles and click the pencil next to the HR tester. 2. Tick a second company, e.g. WBTS, and click Save changes. 3. Sign in as the HR tester and open HR & Admin → People. 4. Back as administrator, untick every company on the same user and save. | E18: The user's line shows both companies. The HR tester's Company filter now offers All my companies, WBE and WBTS. With every company unticked the form refuses: “Leave at least one company ticked”. The Audit Log says which company was added. | F18: Put the tester back to WBE only afterwards if other checks expect it.
A19: ADM-12 | B19: CRM, Inventory & documents | C19: The company is always shown | D19: 1. Sign in as any tester who belongs to one company only. 2. Open HR & Admin → People, then any dashboard. | E19: Beside the list is the company name, e.g. “Company: WBE — WB Engineering”. It cannot be changed — there is nothing else to choose — but the screen says whose records these are.

Sheet Estimator - Sales
A1: Estimator / Sales
A2: Sign in as: | C2: Estimation / Sales Engineer
A3: Takes an enquiry from first call to a priced, approved quotation, and records what the customer ordered.
A4: Tester: | E4: Yellow cells are yours to fill in. Result and Severity have drop-down lists.
A5: ← Back to Summary
A7: Check | B7: Area | C7: Title | D7: Steps | E7: Expected result | F7: Depends on | G7: Result | H7: Severity | I7: What actually happened | J7: Tested by | K7: Date
A8: EST-01 | B8: CRM, Inventory & documents | C8: Log a new enquiry | D8: 1. Open CRM & Estimation → Pipeline and click Log an enquiry. 2. Enter a title, choose the customer Deep Port Logistics FZC, the estimated value and where it came from. 3. Save. | E8: The card appears in the first column. The column's weighted total goes up by less than the full value, because a new enquiry is unlikely to be won yet.
A9: EST-02 | B9: CRM, Inventory & documents | C9: Move an enquiry on | D9: 1. Open your enquiry and click Move it on. 2. Choose the next stage and read the dialog before confirming. | E9: Before you confirm, the dialog shows what the move does to the chance of winning. After it, the card is in the new column and the tracker bar has moved.
A10: EST-03 | B10: CRM, Inventory & documents | C10: Book a site visit, then file the report | D10: 1. On the enquiry click Record beside Site visits. Enter the date and who is going; leave findings empty. Save. 2. Click File the report and save it empty. 3. File it again with what was found. | E10: After booking, the visit shows as booked and the report as still to come. The empty report is refused. With findings, the enquiry shows Site Report Submitted.
A11: EST-04 | B11: CRM, Inventory & documents | C11: Build up an estimate | D11: 1. Open Estimates and click Start an estimate for your enquiry. Set overhead and margin. 2. Add a line measured in metres: material cost, labour hours and rate, plant hours and rate. 3. Add a lump-sum line. | E11: The unit cost adds itself up as you type. The lump-sum line does not ask for a quantity. There is no box to type the selling price.
A12: EST-05 | B12: CRM, Inventory & documents | C12: Take material off with wastage | D12: 1. On the metre line click Add material. Enter how much one metre needs and a wastage of 5%. 2. Save. | E12: The line's material cost now comes from the takeoff, including the 5% wastage.
A13: EST-06 | B13: CRM, Inventory & documents | C13: An estimate with nothing costed cannot be priced | D13: 1. Start a second estimate, add a line with no material, labour, plant or subcontract cost. 2. Click Mark it priced. | E13: Refused: nothing has been costed yet, so there is no price to quote. (A price below cost is also refused unless it is deliberately marked as a loss leader.)
A14: EST-07 | B14: CRM, Inventory & documents | C14: Raise a quotation and check the draft PDF | D14: 1. Open Quotations and click Raise a quotation, choosing your priced estimate. 2. Click Print. | E14: The total comes from the estimate, with no box to change it. The PDF shows DRAFT across every page, the customer, each line with quantity, unit, rate and amount, the total in words and your quotation terms. It shows no cost, margin or markup.
A15: EST-08 | B15: CRM, Inventory & documents | C15: Send a quotation for approval | D15: 1. Click Send for approval. 2. Try to issue it before anyone has approved. | E15: The status is Awaiting approval and the PDF still says DRAFT. It cannot be sent to the customer until management has signed it.
A16: EST-09 | B16: CRM, Inventory & documents | C16: Email the approved quotation | D16: 1. Once approved, click Email it to the customer. 2. Tick the customer contact, and send. | E16: The status becomes Issued. The customer contact receives an email with the quotation PDF attached. The PDF no longer says DRAFT. The send is listed on Settings → Email. | F16: Needs APR-01 approved, and ADM-05 for real email. Without a mail server the button reads “Issue to the customer” and only records where it went.
A17: EST-10 | B17: CRM, Inventory & documents | C17: Revise an issued quotation | D17: 1. On the issued quotation click Raise a revision. 2. Print the old one, then the new one. | E17: The old quotation is marked Superseded and its PDF says SUPERSEDED. The new one is titled Quotation — Revision 2 and goes for approval again.
A18: EST-11 | B18: CRM, Inventory & documents | C18: Record the customer's order | D18: 1. On an issued quotation click They ordered it. 2. Enter their PO number and date, and a value slightly different from the quote. 3. Confirm. | E18: The difference is shown while you type and must be confirmed. A job is created at the customer's value, not the quoted one, with a budget taken from the estimate.
A19: EST-12 | B19: CRM, Inventory & documents | C19: Record a lost enquiry, and see why work is lost | D19: 1. Move an enquiry to Lost. Give the reason and who won it. 2. Open All reports → Where the Work Comes From. | E19: You cannot mark it lost without a reason. The report groups lost work by reason, ordered by value, and lists who took it.
A20: EST-13 | B20: CRM, Inventory & documents | C20: The sales dashboard agrees with the pipeline | D20: 1. Click CRM & Estimation in the menu. It opens on the Dashboard tab. 2. Note Open pipeline and the value beside each stage. 3. Open the Pipeline tab and add up the open deals in one stage. | E20: The stage value on the dashboard is the sum of that stage's deals on the Pipeline. Likely to win is smaller than Open pipeline. Quotations expiring within 14 days are listed, soonest first, and each line opens the quotation list.

Sheet Operations & Directors
A1: Operations & Directors
A2: Sign in as: | C2: Operations Manager, then Director
A3: Signs quotations and purchase orders, and reads the reports that say how the business is doing. Some checks need a second login at the next level.
A4: Tester: | E4: Yellow cells are yours to fill in. Result and Severity have drop-down lists.
A5: ← Back to Summary
A7: Check | B7: Area | C7: Title | D7: Steps | E7: Expected result | F7: Depends on | G7: Result | H7: Severity | I7: What actually happened | J7: Tested by | K7: Date
A8: APR-01 | B8: CRM, Inventory & documents | C8: Approve a quotation through the route | D8: 1. As Operations Manager, open Approvals and approve the estimator's quotation with a comment. 2. As Director, approve it. | E8: After the Operations Manager it waits for the Director. After the Director it is Approved and the estimator can send it. A quotation of AED 500,000 or more also needs the Managing Director. | F8: Needs EST-08.
A9: APR-02 | B9: CRM, Inventory & documents | C9: Approve a purchase order through the route | D9: 1. As Operations Manager, approve the order after the Project Manager has. 2. As Director, approve it. | E9: The order becomes Approved and the storekeeper can now record deliveries against it. An order of AED 50,000 or more also needs the Managing Director. | F9: Needs PRC-07 and PM-02.
A10: APR-03 | B10: CRM, Inventory & documents | C10: Reject with a reason | D10: 1. Reject a pending purchase order or quotation with a comment. | E10: It is Rejected, the comment is kept, and a rejected purchase order prints with REJECTED across the page.
A11: APR-04 | B11: CRM, Inventory & documents | C11: Nobody approves a step above their level | D11: 1. Sign in as the Project Manager and open Approvals while a purchase order is waiting for the Director. | E11: The order is not in the Project Manager's pending list and there is no Approve button for it.
A12: APR-08 | B12: CRM, Inventory & documents | C12: Approve the Project Manager step of material requests | D12: 1. As Operations Manager, open Approvals and approve the two material requests waiting for Project Manager (from SITE-01 and PM-03). | E12: Both move on to Procurement. A senior role may act for a junior step, but the person who raised a request, or already decided one of its steps, cannot. | F12: Needs PM-01 and SITE-03.
A13: APR-05 | B13: CRM, Inventory & documents | C13: Find a report by what you want to know | D13: 1. Open Reports. Search for “late”, then “scrap”, then “win”. | E13: “late” finds Purchase Orders; “scrap” finds Returns from Site; “win” finds Quotations & Hit Rate. The Buying and stores section lists purchase orders, supplier performance, material requests, enquiries, receipts and issues, and returns.
A14: APR-06 | B14: CRM, Inventory & documents | C14: The quotation hit rate is by value | D14: 1. Open CRM & Estimation → Quotations. | E14: The hit rate is worked out by value, not by count. With fewer than three decided quotations it says “too few to call” instead of a percentage.
A15: APR-07 | B15: CRM, Inventory & documents | C15: The pipeline is weighted honestly | D15: 1. Open CRM & Estimation → Pipeline. | E15: The headline figure is the weighted pipeline, smaller than the gross value shown beside it. Each column shows its own weighted total and chance of winning.

Sheet Site Engineer
A1: Site Engineer
A2: Sign in as: | C2: Site Engineer / Planner
A3: Asks the store for material for a job, and is the first to approve a material request.
A4: Tester: | E4: Yellow cells are yours to fill in. Result and Severity have drop-down lists.
A5: ← Back to Summary
A7: Check | B7: Area | C7: Title | D7: Steps | E7: Expected result | F7: Depends on | G7: Result | H7: Severity | I7: What actually happened | J7: Tested by | K7: Date
A8: SITE-01 | B8: CRM, Inventory & documents | C8: Ask for material for a job | D8: 1. Open Inventory & SCM → Material Requests and click Raise a request. 2. Choose an open job, deliver to T-MAIN, and a needed-by date. 3. Add T-CBL-4C16 × 300 metres, T-GLD-M25 × 50, and one line described in words with no item. 4. Click Send for approval. | E8: The request is Submitted. Its card says in a sentence what can be issued from the shelf and what is short.
A9: SITE-02 | B9: CRM, Inventory & documents | C9: Print the request before it is approved | D9: 1. On the request card click Print. | E9: The PDF says NOT APPROVED across the page, lists job, store, needed-by date and lines, and shows no prices.
A10: SITE-03 | B10: CRM, Inventory & documents | C10: Approve someone else's request, not your own | D10: 1. Open Approvals. Find the request you raised in SITE-01 and click Approve. 2. Now approve the Project Manager's request from PM-03, which is waiting for Site Engineer / Planner. | E10: Your own request is refused with “You raised this request, so someone else has to approve it.” The Project Manager's request is approved and moves on to the Project Manager step. If your role cannot approve at all, the screen says so rather than doing nothing. | F10: Needs PM-03. Nobody approves what they raised — the same rule as a cheque needing a second signature.
A11: SITE-05 | B11: Finance & HR | C11: Inventory is in the menu, with only your figures | D11: 1. Look at the menu for Inventory & SCM and click it. 2. Look at what the Stores Dashboard shows. | E11: Inventory & SCM is in the menu and opens the Stores Dashboard. It shows stock value, items running low and requests waiting. There is no Purchase orders panel and no supplier prices — those belong to Procurement.
A12: SITE-04 | B12: CRM, Inventory & documents | C12: A request must ask for something | D12: 1. Start a new request, remove every line, and click Send for approval. | E12: It is refused, asking for at least one line saying what is needed and how much.

Sheet Project Manager
A1: Project Manager
A2: Sign in as: | C2: Project Manager
A3: Approves material requests and purchase orders for the jobs they run.
A4: Tester: | E4: Yellow cells are yours to fill in. Result and Severity have drop-down lists.
A5: ← Back to Summary
A7: Check | B7: Area | C7: Title | D7: Steps | E7: Expected result | F7: Depends on | G7: Result | H7: Severity | I7: What actually happened | J7: Tested by | K7: Date
A8: PM-01 | B8: CRM, Inventory & documents | C8: Approve a material request, one step only | D8: 1. Open Approvals and approve the Site Engineer's request from SITE-01 at its Site Engineer / Planner step — a Project Manager may act for a more junior role. 2. Now try to approve the same request again at the Project Manager step. | E8: The first approval goes through. The second is refused with “You have already decided an earlier step of this request. The next step needs a different person.” It waits for the Operations Manager (APR-08). | F8: Needs SITE-01. One person never walks a request through two levels.
A9: PM-02 | B9: CRM, Inventory & documents | C9: Approve a purchase order | D9: 1. Open Approvals and approve the purchase order waiting for Project Manager. | E9: The order moves on to the Operations Manager. It still cannot be received against. | F9: Needs PRC-07.
A10: PM-03 | B10: CRM, Inventory & documents | C10: Raise your own request | D10: 1. Raise a material request for one of your jobs as in SITE-01. | E10: The request is Submitted and appears in the approvals route starting with the Site Engineer / Planner.

Sheet Procurement
A1: Procurement
A2: Sign in as: | C2: Procurement Officer
A3: Turns approved requests into enquiries and orders: three quotes, a reasoned award, and an order the supplier receives on the company letterhead.
A4: Tester: | E4: Yellow cells are yours to fill in. Result and Severity have drop-down lists.
A5: ← Back to Summary
A7: Check | B7: Area | C7: Title | D7: Steps | E7: Expected result | F7: Depends on | G7: Result | H7: Severity | I7: What actually happened | J7: Tested by | K7: Date
A8: PRC-01 | B8: CRM, Inventory & documents | C8: Final approval of a material request | D8: 1. Open Approvals and approve both material requests waiting for Procurement Officer. | E8: Both requests are Approved. On Material Requests their cards now offer Raise an order. | F8: Needs APR-08.
A9: PRC-02 | B9: CRM, Inventory & documents | C9: Raise an enquiry and ask suppliers | D9: 1. Open Enquiries & Quotes and click Raise an enquiry for the cable and glands. 2. Click Ask suppliers and tick Emirates Cable Trading LLC, Al Masaood Industrial Supplies and Gulf Pipe & Fittings FZE. | E9: There is no price box on the enquiry. All three suppliers appear as columns on the comparison sheet.
A10: PRC-03 | B10: CRM, Inventory & documents | C10: Print the enquiry for each supplier | D10: 1. Click Enquiry under one supplier's name. Then click Print → blank enquiry at the top. | E10: The addressed PDF shows that supplier's name and contact, quantities only, and empty columns for their price, delivery charge, delivery time and validity. The blank copy has an empty To box. Neither shows any price.
A11: PRC-04 | B11: CRM, Inventory & documents | C11: Award needs three suppliers asked | D11: 1. On an enquiry with only two suppliers asked, enter a price for one and try to Award. | E11: Award is not possible, and the screen says three suppliers must be asked first.
A12: PRC-05 | B12: CRM, Inventory & documents | C12: Compare quotations | D12: 1. Enter prices for two of the three suppliers, including carriage, lead time and validity. Leave the third without a reply. | E12: The cheapest price on each line is marked green, which may be a different supplier from the cheapest total. The supplier who did not reply keeps a greyed column.
A13: PRC-06 | B13: CRM, Inventory & documents | C13: Award to a supplier who is not the cheapest | D13: 1. Click Award and choose the more expensive supplier. | E13: You must give a reason, and the extra cost is shown while you type. A draft purchase order is raised at that supplier's prices. The enquiry becomes Awarded and its PDF says CLOSED.
A14: PRC-07 | B14: CRM, Inventory & documents | C14: Check and send the order for approval | D14: 1. Open Purchase Orders and find the draft order raised by the award. 2. Click Print, then Send for approval. | E14: The draft PDF says DRAFT. After sending it is Awaiting approval, the PDF says NOT APPROVED, and there is no Record delivery button yet.
A15: PRC-08 | B15: CRM, Inventory & documents | C15: The approved order as the supplier receives it | D15: 1. After approval, click Print on the order. | E15: The PDF has no mark across it. It shows the supplier with contact, deliver-to store, job, lines with unit price and amount, order total excluding VAT with the amount in words, your purchase order terms, and raised by / approved by with the approval date. | F15: Needs APR-02.
A16: PRC-09 | B16: CRM, Inventory & documents | C16: Raise an order straight from a request | D16: 1. On an approved material request click Raise an order. | E16: The order form opens with the request's job, store and lines already filled in.
A17: PRC-10 | B17: CRM, Inventory & documents | C17: Read supplier performance | D17: 1. Open Supplier Performance. | E17: Each supplier shows on-time-in-full, rejections, replies and price, each with how many orders or inspections it is out of. Where there are too few, it says so rather than showing a percentage.
A18: PRC-11 | B18: Finance & HR | C18: Order work that never arrives in a store | D18: 1. Open Items and add the PRO company’s services — for example “PRO — new employment visa” — with “Keep stock of this” UNTICKED. 2. Check the PRO company is already in Customers & Suppliers. Only Accounts can add one — ask them first if it is missing (FIN-09). 3. Raise a purchase order to them: 3 new visas and 2 labour card renewals at the agreed rates. Send it for approval. 4. Open Stock on Hand and search for the service you added. | E18: The order is raised and goes to Project Manager → Operations Manager → Director like any other. The service does not appear on Stock on Hand at all — it is not on a shelf, and it never pretends to be. | F18: The same applies to equipment hire, subcontract labour, consultancy and camp catering.
A19: PRC-12 | B19: Finance & HR | C19: Close it when the work is done | D19: 1. Once the order is approved, open it and click “Mark work as delivered”. 2. Read the order’s notes. 3. Open the Stores Dashboard. 4. Look at an ordinary material order that has stock on it. | E19: The order becomes Received, and its notes say who confirmed the work and on what date — there is no delivery note, so that sentence is the evidence. It leaves “Orders to receive” on the dashboard. On a material order the button is not offered at all: that material still has to be received into a store. | F19: Needs PRC-11.

Sheet Storekeeper
A1: Storekeeper
A2: Sign in as: | C2: Storekeeper
A3: Receives deliveries against orders, issues material to jobs, moves it between stores, and takes back what returns from site.
A4: Tester: | E4: Yellow cells are yours to fill in. Result and Severity have drop-down lists.
A5: ← Back to Summary
A7: Check | B7: Area | C7: Title | D7: Steps | E7: Expected result | F7: Depends on | G7: Result | H7: Severity | I7: What actually happened | J7: Tested by | K7: Date
A8: STR-01 | B8: CRM, Inventory & documents | C8: Receive a delivery against an approved order | D8: 1. Open Purchase Orders, find the approved order and click Record delivery on the cable line. 2. Enter 200 of the 300 metres, store T-MAIN, bin A-01, and the supplier's delivery note number. | E8: The line shows 200 arrived and 100 outstanding. The order becomes Partly received on its own. | F8: Needs APR-02.
A9: STR-02 | B9: CRM, Inventory & documents | C9: A binned store needs a bin | D9: 1. Record another delivery into T-MAIN without choosing a bin. | E9: It is refused until a bin is chosen.
A10: STR-03 | B10: CRM, Inventory & documents | C10: Print the goods received note | D10: 1. Open Receive & Issue and click Note beside the delivery's reference. | E10: A GOODS RECEIVED NOTE shows the supplier, the store, every item received on that delivery note that day with bin and quantity, the purchase order number, the inspection status, and signature boxes for store, QA/QC and driver. It shows no prices.
A11: STR-04 | B11: CRM, Inventory & documents | C11: Material waiting for inspection cannot be issued | D11: 1. Before QA/QC has inspected, try to issue the delivered cable to a job from Receive & Issue. | E11: Refused. The message says how much can be issued and how much is on the shelf waiting on inspection.
A12: STR-05 | B12: CRM, Inventory & documents | C12: Issue material to a job | D12: 1. After QA/QC passes the cable, record an Issue of 150 metres from T-MAIN, bin A-01, to the job. 2. Try another issue without choosing a job. | E12: The issue is saved and priced from the shelf, not typed. The one with no job is refused because it would put the cost on nothing. | F12: Needs QA-01.
A13: STR-06 | B13: CRM, Inventory & documents | C13: Print the issue note | D13: 1. Click Note beside the issue. | E13: A MATERIAL ISSUE NOTE shows the store, the job it was issued to, the items with value at cost and the total, and signatures for issued by, received by (site) and checked by.
A14: STR-07 | B14: CRM, Inventory & documents | C14: Move stock between stores | D14: 1. Record a Transfer of glands from T-MAIN (bin B-01) to T-SITE1 (bin S-01). 2. Click Note beside it. | E14: Stock on Hand shows the glands moved. Nothing is posted to the accounts. A STOCK TRANSFER NOTE shows both stores.
A15: STR-08 | B15: CRM, Inventory & documents | C15: Cannot issue what is not there | D15: 1. Try to issue an item from a store that holds none of it. | E15: Refused, saying there is none in this store and to receive it first or issue from the store that has it.
A16: STR-09 | B16: CRM, Inventory & documents | C16: Take material back from site | D16: 1. Open Returns from Site and click Record a return for the job. 2. Add the cable twice: 40 metres Reusable and 10 metres Scrap. 3. Read the sentence at the bottom, then save and post it. 4. Try a return of more than the job has out. | E16: The sentence says how much goes back on the shelf and what the job is credited; scrap credits nothing. Returning more than the job has out is refused.
A17: STR-10 | B17: CRM, Inventory & documents | C17: Print the return note | D17: 1. Click Note beside the return. | E17: A MATERIAL RETURN NOTE lists reusable and scrap in separate tables and states the credit to the job once posted. A draft says DRAFT and that nothing has been credited.
A18: STR-11 | B18: CRM, Inventory & documents | C18: Stock on hand and its value | D18: 1. Open Stock on Hand and look at T-CBL-4C16 in T-MAIN. | E18: The quantity equals received minus issued plus reusable returns. Anything at or below its reorder level is highlighted. No balance is negative.
A19: STR-12 | B19: CRM, Inventory & documents | C19: The stores dashboard shows what is running low | D19: 1. Open an item and set its reorder level above what is on hand. Save. 2. Click Inventory & SCM in the menu to open the Stores Dashboard. | E19: Running low counts that item, and it is listed with what is on hand against its reorder level, the lowest first. Stock value by store adds up to the total on the Stock on Hand screen.

Sheet QA-QC & Calibration
A1: QA/QC & Calibration
A2: Sign in as: | C2: QA/QC & Calibration
A3: Passes or fails deliveries that need inspection, and keeps calibrated equipment in date.
A4: Tester: | E4: Yellow cells are yours to fill in. Result and Severity have drop-down lists.
A5: ← Back to Summary
A7: Check | B7: Area | C7: Title | D7: Steps | E7: Expected result | F7: Depends on | G7: Result | H7: Severity | I7: What actually happened | J7: Tested by | K7: Date
A8: QA-01 | B8: CRM, Inventory & documents | C8: Pass a delivery | D8: 1. Open Receive & Issue, find the delivery showing Pending, click Inspect. 2. Pass it and record the certificate number in the notes. | E8: It shows Accepted and the material becomes free to issue straight away. | F8: Needs STR-01, on an item set to need inspection.
A9: QA-02 | B9: CRM, Inventory & documents | C9: Fail a delivery | D9: 1. Inspect another pending delivery and fail it. | E9: It shows Rejected. It stays on the shelf and in stock value but cannot be issued. The inspection cannot be changed afterwards.
A10: QA-03 | B10: CRM, Inventory & documents | C10: Record a calibration | D10: 1. Open Equipment & Calibration and click Calibrate on the torque wrench. 2. Enter a calibration date last month, the result and the certificate number. | E10: The expiry date is worked out from the calibration date, not from today. The sentence at the top updates.
A11: QA-04 | B11: CRM, Inventory & documents | C11: Out-of-calibration equipment cannot go to a job | D11: 1. On Equipment & Calibration, edit a tool that needs calibration and set its status to Out for calibration (or give it a calibration that has already expired). 2. In the same form, choose a job under On job, and save. | E11: Refused, with the reason — away for calibration, or calibration expired. The same tool in date and In service can be put on the job.

Sheet Accounts
A1: Accounts
A2: Sign in as: | C2: Finance / Accounts
A3: Invoices customers, records supplier bills, and checks that stores and payroll reach the books correctly.
A4: Tester: | E4: Yellow cells are yours to fill in. Result and Severity have drop-down lists.
A5: ← Back to Summary
A7: Check | B7: Area | C7: Title | D7: Steps | E7: Expected result | F7: Depends on | G7: Result | H7: Severity | I7: What actually happened | J7: Tested by | K7: Date
A8: FIN-01 | B8: Finance & HR | C8: Draft a tax invoice and print the draft | D8: 1. Open Finance → Invoices → New invoice. Choose a customer with payment terms. 2. Add two lines with different VAT treatments. Save as draft. 3. Click Print. | E8: Totals update as you type, split by VAT rate, and the due date comes from the customer's terms. The PDF says DRAFT across the page and “not a valid tax invoice” under the title.
A9: FIN-02 | B9: Finance & HR | C9: Issue it and print the tax invoice | D9: 1. Click Issue. Then Print. | E9: The invoice takes the next number with no gap. The PDF is titled TAX INVOICE with no mark across it, shows both TRNs, every line with quantity, rate, net, VAT rate and VAT, VAT by rate in the totals, and the total including VAT in words. It cannot now be edited.
A10: FIN-03 | B10: Finance & HR | C10: Credit note against the invoice | D10: 1. Raise a Credit Note, first without naming the invoice, then naming it. Issue and print. | E10: Without the invoice it is refused. The PDF is titled CREDIT NOTE and shows which invoice it adjusts and its date.
A11: FIN-04 | B11: Finance & HR | C11: A supplier's bill is not printed as our invoice | D11: 1. Switch to supplier bills and open one. | E11: There is no Print button to produce it as our tax invoice.
A12: FIN-05 | B12: CRM, Inventory & documents | C12: Material issued to a job reaches job costing | D12: 1. Open Finance → Job Costing for the job the storekeeper issued cable to. | E12: The material cost includes the issue at its shelf value, less any reusable material returned. | F12: Needs STR-05 and STR-09.
A13: FIN-06 | B13: CRM, Inventory & documents | C13: A delivery is stock, not cost | D13: 1. Open the Day Book and find the voucher for the storekeeper's delivery. | E13: The delivery increases inventory against goods received not invoiced. It is not a cost on any job until issued.
A14: FIN-07 | B14: Finance & HR | C14: Reverse charge on a bill from abroad | D14: 1. Enter a supplier bill for an overseas service with the Reverse charge treatment and issue it. | E14: VAT is posted on both sides and nets to nil, and appears in both halves of the VAT return.
A15: FIN-08 | B15: Finance & HR | C15: Who owes us and how late | D15: 1. Open Outstanding & Ageing. | E15: Balances sit in not yet due, 1–30, 31–60, 61–90 and over 90 days, and agree to the customer's statement in Ledgers.
A16: FIN-09 | B16: Finance & HR | C16: A PRO bill: against the order, split for VAT, charged to the right place | D16: 1. If the PRO company is not in Customers & Suppliers yet, add it there first — type Supplier, with its TRN and payment terms. 2. Open Invoices → New, side Purchase. Choose the PRO company. 3. Under “Against purchase order” choose the order from PRC-12. 4. Line 1: their own service fee, VAT treatment Standard, charged to the cost centre Administration & HR. 5. Line 2: the government fees they paid on your behalf (MOHRE, ICP), VAT treatment Out of scope, same cost centre. 6. Save, then Issue it. 7. Open Finance → Cost Centres, then open the purchase order again. | E16: VAT is charged on the service fee only — 5% of that line, nothing on the government fees. The voucher debits the cost and credits the supplier, with both cost lines tagged to Administration & HR. The Cost Centres report shows the total against Administration & HR, and the purchase order now lists the bill under “Billed against this order”. | F16: Needs PRC-12. A line takes a job or a cost centre, never both.

Sheet Finance Controller
A1: Finance Controller
A2: Sign in as: | C2: Finance Controller
A3: Owns the reports, the tax returns and the period lock.
A4: Tester: | E4: Yellow cells are yours to fill in. Result and Severity have drop-down lists.
A5: ← Back to Summary
A7: Check | B7: Area | C7: Title | D7: Steps | E7: Expected result | F7: Depends on | G7: Result | H7: Severity | I7: What actually happened | J7: Tested by | K7: Date
A8: FC-01 | B8: Finance & HR | C8: The books balance | D8: 1. Open Reports → Trial Balance for this year. | E8: Total debits equal total credits.
A9: FC-02 | B9: Finance & HR | C9: VAT return agrees to the ledger | D9: 1. Open Tax → VAT for the current quarter. | E9: Supplies and tax sit in the right boxes, and the return agrees to the two VAT control accounts, or the difference is shown.
A10: FC-03 | B10: Finance & HR | C10: Lock a period | D10: 1. Open Finance → Setup. Under Lock the books, choose the last day of a past month and click Lock. 2. Try to post a journal dated inside it. 3. Try to lock a date in the future. | E10: The back-dated entry is refused. A future date is refused too, because it would block today's own postings. The lock is recorded in the audit log.
A11: FC-04 | B11: Finance & HR | C11: Cash flow forecast | D11: 1. Open Cash Flow Forecast. Turn on Cautious view. | E11: Thirteen weeks from today, opening with the current bank balance, with payroll on payday. Cautious view removes uncertain money coming in and keeps every payment.
A12: FC-05 | B12: Finance & HR | C12: Work in progress | D12: 1. Open Job Costing → Work in Progress. | E12: Each contract shows how far through it is by cost against budget, and whether billing is ahead or behind. A job with no budget says “budget not set” rather than 0%.
A13: FC-07 | B13: Finance & HR | C13: The finance dashboard agrees with the reports | D13: 1. Click Finance & Accounting in the menu. It opens on the Dashboard tab. 2. Note Income this year, Profit this year and Customers owe us. 3. Open Reports → Profit & Loss for 1 January to today, then Outstanding & Ageing. | E13: Income and profit on the dashboard equal the Profit & Loss for the year to date. Customers owe us equals the receivables total on Outstanding & Ageing. Each tile opens the screen its figure comes from.
A14: FC-06 | B14: Finance & HR | C14: Approve the payroll run HR prepared | D14: 1. Open HR → Payroll. Find the run HR prepared in HR-03 and check the totals. 2. Click Approve. Then Mark paid. | E14: The run is Approved, then Paid, and the wage cost is posted to the books. HR can prepare a run but not approve it, so the salary run is always checked by a second person. | F14: Needs HR-03.

Sheet HR
A1: HR
A2: Sign in as: | C2: HR Officer
A3: Employees, attendance, leave, payroll and payslips, and the final settlement when someone leaves. Prepares the payroll run; the Finance Controller approves it.
A4: Tester: | E4: Yellow cells are yours to fill in. Result and Severity have drop-down lists.
A5: ← Back to Summary
A7: Check | B7: Area | C7: Title | D7: Steps | E7: Expected result | F7: Depends on | G7: Result | H7: Severity | I7: What actually happened | J7: Tested by | K7: Date
A8: HR-01 | B8: Finance & HR | C8: Refuse a duplicate person | D8: 1. Add an employee with an Emirates ID already on another employee's record. | E8: Refused, naming the existing record.
A9: HR-02 | B9: Finance & HR | C9: Attendance against a job | D9: 1. Record a day's attendance with in and out times against a job for an employee. | E9: The hours are saved and available to job costing.
A10: HR-03 | B10: Finance & HR | C10: Run payroll | D10: 1. Open Payroll and run the month. | E10: Every employee has basic, allowances, overtime, deductions and net pay. Anyone missing a salary or bank details is held back and named.
A11: HR-04 | B11: CRM, Inventory & documents | C11: Print payslips for the whole run | D11: 1. On the draft run, click Print → all payslips. 2. Look for an Approve button on the run. 3. After the Finance Controller has approved it (FC-06), print again. | E11: The draft prints with DRAFT on every page. There is no Approve button for HR — the run shows “Waiting for the Finance Controller to approve”. After approval there is no mark. Each employee is on a page of their own with earnings, deductions, net pay in words, and the bank shown as the bank name and the last four characters of the account only. | F11: FC-06 approves the run.
A12: HR-05 | B12: CRM, Inventory & documents | C12: Print one employee's payslip | D12: 1. Click Payslip on one employee's row, ideally someone who joined part-way through the month. | E12: One page for that employee. A part month shows the days behind the figure, e.g. “12 of 30 days on 3,000.00”.
A13: HR-06 | B13: Finance & HR | C13: Payroll reaches the accounts | D13: 1. After the Finance Controller approves the run and marks it paid, ask Accounts to find the payroll voucher in the Day Book. | E13: The wage cost is posted without anyone typing a journal.
A14: HR-07 | B14: Finance & HR | C14: WPS file for the bank | D14: 1. Generate the WPS file for the approved run. | E14: The IBAN, MOL Person ID and routing code are checked first, and anyone who would make the bank reject the file is named.
A15: HR-08 | B15: CRM, Inventory & documents | C15: Final settlement statement | D15: 1. Open Separation, record a resignation for an employee with over five years' service. 2. Click Statement while it is Draft, then approve it and click Statement again. | E15: Gratuity is 21 days' basic a year for the first five years and 30 days after, capped at two years' pay. The draft PDF says DRAFT; the approved one does not. It carries the employee's declaration and signature boxes.
A16: HR-09 | B16: Finance & HR | C16: Document expiry warnings | D16: 1. Open Compliance & Expiry. | E16: Visas, Emirates IDs, passports and labour cards due to expire are listed before they lapse.
A17: HR-10 | B17: Finance & HR | C17: The HR dashboard: today, and what is waiting | D17: 1. Click HR & Admin in the menu. It opens on the Dashboard tab. 2. Mark today's attendance for two people, then come back to the dashboard. 3. Raise a leave request for someone and come back again. | E17: Present today goes up by the two you marked, and Not yet marked goes down. Leave to decide counts the new request and lists it with its start date. Documents lapsing lists visas, Emirates IDs, labour cards and passports expiring within 60 days. No salary or pay figure appears anywhere on the dashboard.

Sheet Site Timekeeper
A1: Site Timekeeper
A2: Sign in as: | C2: Site Timekeeper
A3: Records the daily muster on site and the hours against each job — and can see nothing else.
A4: Tester: | E4: Yellow cells are yours to fill in. Result and Severity have drop-down lists.
A5: ← Back to Summary
A7: Check | B7: Area | C7: Title | D7: Steps | E7: Expected result | F7: Depends on | G7: Result | H7: Severity | I7: What actually happened | J7: Tested by | K7: Date
A8: TK-01 | B8: Finance & HR | C8: Record the day's muster | D8: 1. Open HR → Attendance & Muster. 2. Mark today's attendance for three workers — present, absent, half-day — with in and out times and the job each worked on. Save. | E8: The muster is saved and the hours sit against each job, ready for job costing.
A9: TK-02 | B9: Finance & HR | C9: Only attendance, nothing else | D9: 1. Look at the menu. 2. Type /hr/payroll at the end of the address and press Enter. Then try /hr and /finance. | E9: The menu shows only the Dashboard and HR & Admin. HR & Admin opens an HR dashboard showing only today's muster, with Attendance & Muster as the one other tab. Every other address returns you to the dashboard — no salaries, payroll, employee profiles or finance screens are shown.
